[
  {
    "path": "Videos/ChapterUnlocks/1.mp4",
    "hash": "OMPj5dvEcmPuA+T/0zzMEQ=="
  },
  {
    "path": "Videos/ChapterUnlocks/10.mp4",
    "hash": "dmtaXqLLSrjjPx6GdaUGQQ=="
  },
  {
    "path": "Videos/ChapterUnlocks/11.mp4",
    "hash": "vcwDpx6bjE5wwiMTzwpTPg=="
  },
  {
    "path": "Videos/ChapterUnlocks/12.mp4",
    "hash": "szebfQfI9yqSmiCXsWxNpw=="
  },
  {
    "path": "Videos/ChapterUnlocks/13.mp4",
    "hash": "FYY5XH7DQ9SjaCIVXusIxQ=="
  },
  {
    "path": "Videos/ChapterUnlocks/2.mp4",
    "hash": "I5v2UKp9UoAIv6m+OQCiyA=="
  },
  {
    "path": "Videos/ChapterUnlocks/3.mp4",
    "hash": "4OBMuVElQoYvGFYzuaW7tQ=="
  },
  {
    "path": "Videos/ChapterUnlocks/4.mp4",
    "hash": "kIB4KjTQoSG8wVfEY45nWw=="
  },
  {
    "path": "Videos/ChapterUnlocks/5.mp4",
    "hash": "avC5Qyq8JnVwnljEZW9nSQ=="
  },
  {
    "path": "Videos/ChapterUnlocks/6.mp4",
    "hash": "CLCGsfkDaSCykaxfPwLtjQ=="
  },
  {
    "path": "Videos/ChapterUnlocks/7.mp4",
    "hash": "jojc9KYEcATEh9qbtSoIpQ=="
  },
  {
    "path": "Videos/ChapterUnlocks/8.mp4",
    "hash": "E1CjUU/6IsBNhXcvYoQHTQ=="
  },
  {
    "path": "Videos/ChapterUnlocks/9.mp4",
    "hash": "h5UGogi6lYrExFhLCb+Mkg=="
  },
  {
    "path": "Videos/Gacha/1003.mp4",
    "hash": "YLEL5zGbmquDeITf5bVsHQ=="
  },
  {
    "path": "Videos/Gacha/1006.mp4",
    "hash": "F4kiB4M94WQxVp+gOh7rkw=="
  },
  {
    "path": "Videos/Gacha/1009.mp4",
    "hash": "ZO+R8R1GorR3+ebdMZ6/8w=="
  },
  {
    "path": "Videos/Gacha/1010.mp4",
    "hash": "VyTnSBm4c49FXyChKn+p4w=="
  },
  {
    "path": "Videos/Gacha/1011.mp4",
    "hash": "eRPMhHGR5sesPhuQqXGBAA=="
  },
  {
    "path": "Videos/Gacha/1012.mp4",
    "hash": "8qg7JrN2NpozZXmVYHrosg=="
  },
  {
    "path": "Videos/Gacha/1013.mp4",
    "hash": "MUAikSSCU/iBexftGo579A=="
  },
  {
    "path": "Videos/Gacha/1015.mp4",
    "hash": "fc1ZFjXbu9ozzrluRRI9hw=="
  },
  {
    "path": "Videos/Gacha/1016.mp4",
    "hash": "PtayhjRpMqU7Fh34K4tnZw=="
  },
  {
    "path": "Videos/Gacha/1020.mp4",
    "hash": "BTRs9adRVN7yycHfShDqIQ=="
  },
  {
    "path": "Videos/Gacha/1021.mp4",
    "hash": "ZFQ1GdvdtJcuIW1YxCNJWw=="
  },
  {
    "path": "Videos/Gacha/1025.mp4",
    "hash": "Z1GPBnVaGlHZ7e+2i5zSrA=="
  },
  {
    "path": "Videos/SpecialSkills/610401.mp4",
    "hash": "S7om5AGWEvYoEZHpaJisjQ=="
  },
  {
    "path": "Videos/SpecialSkills/610402.mp4",
    "hash": "eefH7cs5jKoNVjvCufLiKQ=="
  },
  {
    "path": "Videos/SpecialSkills/612401.mp4",
    "hash": "2JBnhm2Msi07BNY3RIMElw=="
  },
  {
    "path": "Videos/SpecialSkills/613401.mp4",
    "hash": "sqOdfdCP8ttipFbiBizkNA=="
  },
  {
    "path": "Videos/SpecialSkills/61401.mp4",
    "hash": "LfYtsXoFgI6sWbaLGJMdgQ=="
  },
  {
    "path": "Videos/SpecialSkills/615401.mp4",
    "hash": "j/gCRl9tmKJHPBnskt0sLA=="
  },
  {
    "path": "Videos/SpecialSkills/616401.mp4",
    "hash": "2Q4v5/CePXfSQi9wGOVdSg=="
  },
  {
    "path": "Videos/SpecialSkills/617401.mp4",
    "hash": "iLMguEFzPK8ejVLYdazfXw=="
  },
  {
    "path": "Videos/SpecialSkills/619401.mp4",
    "hash": "t5dtGlkbnqP7nbSyhzuUYQ=="
  },
  {
    "path": "Videos/SpecialSkills/620401.mp4",
    "hash": "eUljWb0/kJX3FQyv8yTY7g=="
  },
  {
    "path": "Videos/SpecialSkills/620402.mp4",
    "hash": "E1h9+Ux6K6lFBPwbuGolOw=="
  },
  {
    "path": "Videos/SpecialSkills/621401.mp4",
    "hash": "bM0BbQR8gIBtrX/zptDWNQ=="
  },
  {
    "path": "Videos/SpecialSkills/623401.mp4",
    "hash": "kTDTjltHm7NY6HYGDbOF9g=="
  },
  {
    "path": "Videos/SpecialSkills/62401.mp4",
    "hash": "zqxDaEC/+KR9iapI3/MVXQ=="
  },
  {
    "path": "Videos/SpecialSkills/624401.mp4",
    "hash": "Pu3Ac1ijyyA2uARmIT9jlQ=="
  },
  {
    "path": "Videos/SpecialSkills/624402.mp4",
    "hash": "6c+rcw7WX4VoIbiq5pGMJQ=="
  },
  {
    "path": "Videos/SpecialSkills/626401.mp4",
    "hash": "nga24E3YGb74uFwf9ZRw2A=="
  },
  {
    "path": "Videos/SpecialSkills/627401.mp4",
    "hash": "4aYDAYGoNZS0kKJOnKf3Hw=="
  },
  {
    "path": "Videos/SpecialSkills/628401.mp4",
    "hash": "5KK2bHq5jr7jGQ0jQE1zrw=="
  },
  {
    "path": "Videos/SpecialSkills/629401.mp4",
    "hash": "hnWQTfbXg16Y6MA7zniuVg=="
  },
  {
    "path": "Videos/SpecialSkills/632401.mp4",
    "hash": "R/NoQ/SUVemUqpJWVz9Bzw=="
  },
  {
    "path": "Videos/SpecialSkills/633401.mp4",
    "hash": "11n7/9h+Z/odngeVpabfGw=="
  },
  {
    "path": "Videos/SpecialSkills/634401.mp4",
    "hash": "Nifcpg8zixdCk86ijwNc/Q=="
  },
  {
    "path": "Videos/SpecialSkills/635401.mp4",
    "hash": "AkqrglX8W6qoVE1DxhBiAA=="
  },
  {
    "path": "Videos/SpecialSkills/635402.mp4",
    "hash": "N1mbSCWnOxZwbbKGGL+vIA=="
  },
  {
    "path": "Videos/SpecialSkills/636401.mp4",
    "hash": "yYucyL1jo8XgiI3Gzdt0HQ=="
  },
  {
    "path": "Videos/SpecialSkills/637401.mp4",
    "hash": "mn4D1sT8a6VIhP7HIhCWiA=="
  },
  {
    "path": "Videos/SpecialSkills/638401.mp4",
    "hash": "oQq2Rjte56LLhFmQ4shKBw=="
  },
  {
    "path": "Videos/SpecialSkills/640401.mp4",
    "hash": "gRtpIvVKFKzBBQG810uTew=="
  },
  {
    "path": "Videos/SpecialSkills/641401.mp4",
    "hash": "gI9tk4n/1od9YwqlxtKKUQ=="
  },
  {
    "path": "Videos/SpecialSkills/642401.mp4",
    "hash": "IPQTKadcDSEpsfbihTLoWg=="
  },
  {
    "path": "Videos/SpecialSkills/643401.mp4",
    "hash": "6oIFrXqP9CiOnZ39yYMVOw=="
  },
  {
    "path": "Videos/SpecialSkills/645401.mp4",
    "hash": "/rHYF6xH3fwmXdRFlMYXnw=="
  },
  {
    "path": "Videos/SpecialSkills/646401.mp4",
    "hash": "rZkkXWZ4UeR26zk8iPZ6Lg=="
  },
  {
    "path": "Videos/SpecialSkills/647401.mp4",
    "hash": "yvoNTPdsTYcW3kDMOmXoHQ=="
  },
  {
    "path": "Videos/SpecialSkills/649401.mp4",
    "hash": "7rbsNuojEdPLOgJ3ywHfvw=="
  },
  {
    "path": "Videos/SpecialSkills/649402.mp4",
    "hash": "BMkPrWINvvXl3moF36KG7w=="
  },
  {
    "path": "Videos/SpecialSkills/650401.mp4",
    "hash": "1uid8AbuNhBJdqfUBab9JA=="
  },
  {
    "path": "Videos/SpecialSkills/651401.mp4",
    "hash": "zchg9pm5LPu3dHLiG/XbbA=="
  },
  {
    "path": "Videos/SpecialSkills/652401.mp4",
    "hash": "kuWy/ZpLEknO9fU+YkeLLA=="
  },
  {
    "path": "Videos/SpecialSkills/653401.mp4",
    "hash": "UE4XgRoABtkGu4F4qjZITg=="
  },
  {
    "path": "Videos/SpecialSkills/65401.mp4",
    "hash": "N96YSy9q+MXVUg13oOtZpA=="
  },
  {
    "path": "Videos/SpecialSkills/654401.mp4",
    "hash": "1t2jZVr0arSMMQxkuZjEag=="
  },
  {
    "path": "Videos/SpecialSkills/656401.mp4",
    "hash": "iczTQREWwhxCIm5FQRhMkA=="
  },
  {
    "path": "Videos/SpecialSkills/658401.mp4",
    "hash": "DmfDGPpCJCGUhF2P9RNHxQ=="
  },
  {
    "path": "Videos/SpecialSkills/659401.mp4",
    "hash": "bkLBWnUAcJUxskLZlfQM1A=="
  },
  {
    "path": "Videos/SpecialSkills/660401.mp4",
    "hash": "5IIEh+BLyvzglqvuTwRZiw=="
  },
  {
    "path": "Videos/SpecialSkills/663401.mp4",
    "hash": "Zf06/6N2mk6nmtLEnQT/VA=="
  },
  {
    "path": "Videos/SpecialSkills/66401.mp4",
    "hash": "iBIdVZCdzAvX0er0p99Jvg=="
  },
  {
    "path": "Videos/SpecialSkills/664401.mp4",
    "hash": "tvARCFpXlzdqAT9UL+1MeQ=="
  },
  {
    "path": "Videos/SpecialSkills/666401.mp4",
    "hash": "NHBPxSLyMz6E3lrP4YIN/Q=="
  },
  {
    "path": "Videos/SpecialSkills/667401.mp4",
    "hash": "NpQwuUGLzXJs6/ssgfkeyg=="
  },
  {
    "path": "Videos/SpecialSkills/668401.mp4",
    "hash": "aa5PXeGUH5Z40KFakSPibg=="
  },
  {
    "path": "Videos/SpecialSkills/669401.mp4",
    "hash": "9zdTVF1ru97/+5sO1qP0wg=="
  },
  {
    "path": "Videos/SpecialSkills/67401.mp4",
    "hash": "wvxHFahs0dx1M0/Xp9hXAg=="
  },
  {
    "path": "Videos/SpecialSkills/68401.mp4",
    "hash": "e3u41EECJRm/Qpcu7ht0aA=="
  },
  {
    "path": "Videos/SpecialSkills/69401.mp4",
    "hash": "SQzpD4kTQiNl5BQTFtlZOw=="
  },
  {
    "path": "Videos/Title/title_pv.mp4",
    "hash": "KpvUTXfibIYoGHz93hCyWA=="
  },
  {
    "path": "Videos/Tutorial/prologue.mp4",
    "hash": "/xF3bdN2z1TSdNgM8VJCqA=="
  }
]